ordered_set_37/__init__.py
Ordered_set_37-2.0.dist-info/LICENSE.md
Ordered_set_37-2.0.dist-info/METADATA
Ordered_set_37-2.0.dist-info/WHEEL
Ordered_set_37-2.0.dist-info/top_level.txt
Ordered_set_37-2.0.dist-info/RECORD
