Metadata-Version: 2.1
Name: Ordered-set-37
Version: 2.0
Summary: Dead simple & fast ordered set using python's 3.7+ dict.
Home-page: https://github.com/bustawin/ordered-set-37
Author: Xavier Bustamante
Author-email: xavier@bustawin.com
License: Unlicense
Project-URL: Documentation, https://github.com/bustawin/ordered-set-37
Project-URL: Code, https://github.com/bustawin/ordered-set-37
Project-URL: Issue tracker, https://github.com/bustawin/ordered-set-37/issues/
Classifier: Development Status :: 2 - Pre-Alpha
Classifier: Operating System :: OS Independent
Classifier: Programming Language :: Python :: 3 :: Only
Classifier: Programming Language :: Python :: 3.7
Classifier: Programming Language :: Python :: 3.8
Classifier: Programming Language :: Python :: 3.9
Requires-Python: >=3.7
License-File: LICENSE.md
Provides-Extra: test
Requires-Dist: pytest ; extra == 'test'
Requires-Dist: mypy ; extra == 'test'
